README.txt
setup.py
dsk2obj/__init__.py
dsk2obj/main.py
dsk2obj.egg-info/PKG-INFO
dsk2obj.egg-info/SOURCES.txt
dsk2obj.egg-info/dependency_links.txt
dsk2obj.egg-info/requires.txt
dsk2obj.egg-info/top_level.txt