Metadata-Version: 1.2
Name: dsk2obj
Version: 0.5
Summary: generates an obj file from a bds file (dsk kernel) and dsiplays it
Home-page: UNKNOWN
Author: Alfredo Escalante
Author-email: alfredoescalante95@gmail.com
License: UNKNOWN
Platform: UNKNOWN
Requires-Python: >=3
